UniversalBackupValidator/__init__.py
UniversalBackupValidator/cli.py
validators/__init__.py
validators/sevenz_validator.py
validators/tar_validator.py
validators/zip_validator.py
UniversalBackupValidator-1.0.0.dist-info/LICENSE
UniversalBackupValidator-1.0.0.dist-info/METADATA
UniversalBackupValidator-1.0.0.dist-info/WHEEL
UniversalBackupValidator-1.0.0.dist-info/entry_points.txt
UniversalBackupValidator-1.0.0.dist-info/top_level.txt
UniversalBackupValidator-1.0.0.dist-info/RECORD
