Metadata-Version: 2.1
Name: UniversalBackupValidator
Version: 1.0.0
Summary: A tool for validating and verifying backup files.
Home-page: https://github.com/tudos4/UniversalBackupValidator
Author: tudos4
Author-email: your_email@example.com
Classifier: Programming Language :: Python :: 3
Classifier: License :: OSI Approved :: MIT License
Classifier: Operating System :: OS Independent
Requires-Python: >=3.7
License-File: LICENSE
Requires-Dist: colorama>=0.4.4
